AUTHORS
MANIFEST.in
README.rst
setup.py
cropper/__init__.py
cropper/admin.py
cropper/forms.py
cropper/models.py
cropper/settings.py
cropper/signals.py
cropper/urls.py
cropper/views.py
cropper/locale/ru/LC_MESSAGES/django.mo
cropper/locale/ru/LC_MESSAGES/django.po
cropper/migrations/0001_initial.py
cropper/migrations/0002_auto__del_field_original_name__del_field_cropped_name.py
cropper/migrations/0003_auto__del_field_cropped_w_display__del_field_cropped_h_display.py
cropper/migrations/__init__.py
cropper/static/cropper/css/jquery.Jcrop.css
cropper/static/cropper/img/Jcrop.gif
cropper/static/cropper/js/cropper.js
cropper/static/cropper/js/jquery.Jcrop.js
cropper/static/cropper/js/jquery.color.js
cropper/static/cropper/js/jquery.min.js
cropper/templates/cropper/base.html
cropper/templates/cropper/crop.html
cropper/templates/cropper/upload.html
cropper/tests/__init__.py
django_image_cropper.egg-info/PKG-INFO
django_image_cropper.egg-info/SOURCES.txt
django_image_cropper.egg-info/dependency_links.txt
django_image_cropper.egg-info/requires.txt
django_image_cropper.egg-info/top_level.txt