Metadata-Version: 1.1
Name: django-image-cropper
Version: 0.3.0
Summary: This app allows upload and crop images
Home-page: http://bitbucket.org/marazmiki/django-image-cropper/
Author: marazmiki
Author-email: marazmiki@gmail.com
License: MIT license
Download-URL: http://bitbucket.org/marazmiki/django-image-cropper/get/tip.zip
Platform: UNKNOWN
Classifier: Development Status :: 4 - Beta
Classifier: Framework :: Django
Classifier: Intended Audience :: Developers
Classifier: License :: OSI Approved :: MIT License
Classifier: Programming Language :: Python
Classifier: Topic :: Software Development :: Libraries :: Python Modules
